mindspore/.commit_id
mindspore/ConcurrencyCheck.dll
mindspore/CppBuildInsights.dll
mindspore/CppCoreCheck.dll
mindspore/EnumIndex.dll
mindspore/EspXEngine.dll
mindspore/HResultCheck.dll
mindspore/KernelTraceControl.dll
mindspore/LocalESPC.dll
mindspore/Microsoft.Diagnostics.Tracing.EventSource.dll
mindspore/Microsoft.VisualStudio.RemoteControl.dll
mindspore/Microsoft.VisualStudio.Telemetry.dll
mindspore/Microsoft.VisualStudio.Utilities.Internal.dll
mindspore/Newtonsoft.Json.dll
mindspore/System.Runtime.CompilerServices.Unsafe.dll
mindspore/VariantClear.dll
mindspore/__init__.py
mindspore/_c_dataengine.cp310-win_amd64.pyd
mindspore/_c_expression.cp310-win_amd64.pyd
mindspore/_c_mindrecord.cp310-win_amd64.pyd
mindspore/_check_jit_forbidden_api.py
mindspore/_checkparam.py
mindspore/_profiler.py
mindspore/amp.py
mindspore/atlprov.dll
mindspore/avcodec-59.dll
mindspore/avdevice-59.dll
mindspore/avfilter-8.dll
mindspore/avformat-59.dll
mindspore/avutil-57.dll
mindspore/c1.dll
mindspore/c1xx.dll
mindspore/c2.dll
mindspore/cfgpersist.dll
mindspore/clang_rt.asan_dbg_dynamic-x86_64.dll
mindspore/clang_rt.asan_dynamic-x86_64.dll
mindspore/context.py
mindspore/d3dcompiler_47.dll
mindspore/default_config.py
mindspore/device_manager.py
mindspore/dnnl.dll
mindspore/dpcmi.dll
mindspore/jpeg62.dll
mindspore/log.py
mindspore/mindspore_backend_common.dll
mindspore/mindspore_backend_manager.dll
mindspore/mindspore_common.dll
mindspore/mindspore_core.dll
mindspore/mindspore_dump.dll
mindspore/mindspore_frontend.dll
mindspore/mindspore_glog.dll
mindspore/mindspore_memory_pool.dll
mindspore/mindspore_ms_backend.dll
mindspore/mindspore_ops.dll
mindspore/mindspore_ops_host.dll
mindspore/mindspore_ops_kernel_common.dll
mindspore/mindspore_profiler.dll
mindspore/mindspore_pyboost.dll
mindspore/mindspore_pynative.dll
mindspore/mindspore_res_manager.dll
mindspore/mindspore_runtime_pipeline.dll
mindspore/msobj140.dll
mindspore/mspdb140.dll
mindspore/mspdbcore.dll
mindspore/mspdbst.dll
mindspore_dev-2.6.0.dev20250330.dist-info/METADATA
mindspore_dev-2.6.0.dev20250330.dist-info/WHEEL
mindspore_dev-2.6.0.dev20250330.dist-info/entry_points.txt
mindspore_dev-2.6.0.dev20250330.dist-info/top_level.txt
mindspore_dev-2.6.0.dev20250330.dist-info/RECORD
