Metadata-Version: 2.1
Name: mindspore-dev
Version: 2.6.0.dev20250330
Summary: MindSpore is a new open source deep learning training/inference framework that could be used for mobile, edge and cloud scenarios.
Home-page: https://www.mindspore.cn
Author: The MindSpore Authors
Author-email: contact@mindspore.cn
License: Apache 2.0
Download-URL: https://github.com/mindspore-ai/mindspore/tags
Project-URL: Sources, https://github.com/mindspore-ai/mindspore
Project-URL: Issue Tracker, https://github.com/mindspore-ai/mindspore/issues
Keywords: mindspore machine learning
Platform: UNKNOWN
Classifier: Development Status :: 5 - Production/Stable
Classifier: Environment :: Console
Classifier: Intended Audience :: Science/Research
Classifier: Intended Audience :: Developers
Classifier: License :: OSI Approved :: Apache Software License
Classifier: Programming Language :: Python :: 3 :: Only
Classifier: Programming Language :: Python :: 3.7
Classifier: Programming Language :: Python :: 3.8
Classifier: Programming Language :: Python :: 3.9
Classifier: Programming Language :: Python :: 3.10
Classifier: Programming Language :: Python :: 3.11
Classifier: Programming Language :: C++
Classifier: Topic :: Scientific/Engineering
Classifier: Topic :: Scientific/Engineering :: Artificial Intelligence
Classifier: Topic :: Software Development
Classifier: Topic :: Software Development :: Libraries
Classifier: Topic :: Software Development :: Libraries :: Python Modules
Requires-Python: >=3.7
Requires-Dist: numpy <2.0.0,>=1.20.0
Requires-Dist: protobuf >=3.13.0
Requires-Dist: asttokens >=2.0.4
Requires-Dist: pillow >=6.2.0
Requires-Dist: scipy >=1.5.4
Requires-Dist: packaging >=20.0
Requires-Dist: psutil >=5.6.1
Requires-Dist: astunparse >=1.6.3
Requires-Dist: safetensors >=0.4.0
Requires-Dist: dill >=0.3.7
